{
  "generated_at": "2026-03-17 11:29",
  "total": 97,
  "source_stats": {
    "idshare001.me": 2,
    "ccbaohe.com/appleID": 54,
    "tkbaohe.com": 21,
    "id.btvda.top": 11,
    "id.bocchi2b.top": 9
  },
  "accounts": [
    {
      "id": "1082704efbcb",
      "email": "idshare.me_u223nw@icloud.com",
      "password": "&rTb0Y42",
      "status": "正常",
      "country": "美国",
      "checked_at": "2026-03-17 10:49:45",
      "source": "idshare001.me",
      "updated_at": "2026-03-17 10:49:45"
    },
    {
      "id": "89a863733098",
      "email": "dtppqkm708273@icloud.com",
      "password": "#Fq0ftAx",
      "status": "正常",
      "country": "美国",
      "checked_at": "2026-03-17 10:49:45",
      "source": "idshare001.me",
      "updated_at": "2026-03-17 10:49:45"
    },
    {
      "id": "93df62e1db45",
      "email": "leeesk62701@icloud.com",
      "password": "pjGpTzyp8p",
      "status": "正常",
      "country": "越南",
      "checked_at": "2026-03-17 11:29:38",
      "source": "ccbaohe.com/appleID",
      "updated_at": "2026-03-17 11:26:55"
    },
    {
      "id": "db23d0ce6c66",
      "email": "lindaodw27786@icloud.com",
      "password": "ZJ2CWe3EtR",
      "status": "正常",
      "country": "美国",
      "checked_at": "2026-03-17 11:29:38",
      "source": "ccbaohe.com/appleID",
      "updated_at": "2026-03-17 11:26:55"
    },
    {
      "id": "bb48f450a32e",
      "email": "ogurandy44131@icloud.com",
      "password": "69R2dsfCsr",
      "status": "正常",
      "country": "美国",
      "checked_at": "2026-03-17 11:29:38",
      "source": "ccbaohe.com/appleID",
      "updated_at": "2026-03-17 11:26:55"
    },
    {
      "id": "826a422197cf",
      "email": "reginaamx00410@icloud.com",
      "password": "TvwEN2EX2z",
      "status": "正常",
      "country": "中国大陆",
      "checked_at": "2026-03-17 11:29:38",
      "source": "ccbaohe.com/appleID",
      "updated_at": "2026-03-17 11:26:55"
    },
    {
      "id": "0e61ce641416",
      "email": "brigittejpx20705@icloud.com",
      "password": "pRNXRdxJ1G",
      "status": "正常",
      "country": "美国",
      "checked_at": "2026-03-17 11:29:38",
      "source": "ccbaohe.com/appleID",
      "updated_at": "2026-03-17 11:26:55"
    },
    {
      "id": "b250fa22f996",
      "email": "christaxki84479@icloud.com",
      "password": "mMbCNubem2",
      "status": "正常",
      "country": "美国",
      "checked_at": "2026-03-17 11:29:38",
      "source": "ccbaohe.com/appleID",
      "updated_at": "2026-03-17 11:26:55"
    },
    {
      "id": "9c9fa002b4a9",
      "email": "nikkisla35062@icloud.com",
      "password": "xFQpRDe5es",
      "status": "正常",
      "country": "越南",
      "checked_at": "2026-03-17 11:29:38",
      "source": "ccbaohe.com/appleID",
      "updated_at": "2026-03-17 11:26:55"
    },
    {
      "id": "75590c6cb5ff",
      "email": "vnrroger55629@icloud.com",
      "password": "bsHteJJ5MR",
      "status": "正常",
      "country": "美国",
      "checked_at": "2026-03-17 11:29:38",
      "source": "ccbaohe.com/appleID",
      "updated_at": "2026-03-17 11:26:55"
    },
    {
      "id": "7ab4a3a6db16",
      "email": "robertoxbe53275@icloud.com",
      "password": "pYbxnvhQ13",
      "status": "正常",
      "country": "美国",
      "checked_at": "2026-03-17 11:29:38",
      "source": "ccbaohe.com/appleID",
      "updated_at": "2026-03-17 11:26:55"
    },
    {
      "id": "b6cb5e692e2c",
      "email": "dorothyvma13664@icloud.com",
      "password": "nRVh5H6zNs",
      "status": "正常",
      "country": "印尼",
      "checked_at": "2026-03-17 11:29:38",
      "source": "ccbaohe.com/appleID",
      "updated_at": "2026-03-17 11:26:55"
    },
    {
      "id": "6e6e7c4e0113",
      "email": "jenniferhwr56308@icloud.com",
      "password": "4KKnX2udA2",
      "status": "正常",
      "country": "美国",
      "checked_at": "2026-03-17 11:29:38",
      "source": "ccbaohe.com/appleID",
      "updated_at": "2026-03-17 11:26:55"
    },
    {
      "id": "35e653587ce9",
      "email": "bridgetmjj43006@icloud.com",
      "password": "Qq7VhhKB8y",
      "status": "正常",
      "country": "越南",
      "checked_at": "2026-03-17 11:29:38",
      "source": "ccbaohe.com/appleID",
      "updated_at": "2026-03-17 11:26:55"
    },
    {
      "id": "f89b59a984ef",
      "email": "terryxcu57301@icloud.com",
      "password": "Xq2U4xKsZu",
      "status": "正常",
      "country": "台湾",
      "checked_at": "2026-03-17 11:29:38",
      "source": "ccbaohe.com/appleID",
      "updated_at": "2026-03-17 11:26:55"
    },
    {
      "id": "e68ec140b113",
      "email": "eunolga36601@icloud.com",
      "password": "pQAPGW9mBn",
      "status": "正常",
      "country": "越南",
      "checked_at": "2026-03-17 11:29:38",
      "source": "ccbaohe.com/appleID",
      "updated_at": "2026-03-17 11:26:55"
    },
    {
      "id": "be1d779bbae3",
      "email": "janeymct61212@icloud.com",
      "password": "uXMwT5UB4x",
      "status": "正常",
      "country": "美国",
      "checked_at": "2026-03-17 11:29:38",
      "source": "ccbaohe.com/appleID",
      "updated_at": "2026-03-17 11:26:55"
    },
    {
      "id": "e07a6335b545",
      "email": "andreagarrettzejat@icloud.com",
      "password": "YB5TEQCyJa",
      "status": "正常",
      "country": "美国",
      "checked_at": "2026-03-17 11:29:38",
      "source": "ccbaohe.com/appleID",
      "updated_at": "2026-03-17 11:26:55"
    },
    {
      "id": "f9edb5302a0a",
      "email": "brandywilliamssmdun@icloud.com",
      "password": "gFY7BedG2y",
      "status": "正常",
      "country": "美国",
      "checked_at": "2026-03-17 11:29:38",
      "source": "ccbaohe.com/appleID",
      "updated_at": "2026-03-17 11:26:55"
    },
    {
      "id": "afd6dad362f3",
      "email": "jasonbennettnetbz@icloud.com",
      "password": "r31Y3U4Efs",
      "status": "正常",
      "country": "美国",
      "checked_at": "2026-03-17 11:29:38",
      "source": "ccbaohe.com/appleID",
      "updated_at": "2026-03-17 11:26:55"
    },
    {
      "id": "bd02d5065e2f",
      "email": "ritagordonwlsqy@icloud.com",
      "password": "fDjkvnvse4",
      "status": "正常",
      "country": "美国",
      "checked_at": "2026-03-17 11:29:38",
      "source": "ccbaohe.com/appleID",
      "updated_at": "2026-03-17 11:26:55"
    },
    {
      "id": "19f66ab47bde",
      "email": "deniserothomalv@icloud.com",
      "password": "hbv6C7NYJA",
      "status": "正常",
      "country": "美国",
      "checked_at": "2026-03-17 11:29:38",
      "source": "ccbaohe.com/appleID",
      "updated_at": "2026-03-17 11:26:55"
    },
    {
      "id": "84fb57009197",
      "email": "amycolonfddpe@icloud.com",
      "password": "2XaN4zVgvF",
      "status": "正常",
      "country": "美国",
      "checked_at": "2026-03-17 11:29:38",
      "source": "ccbaohe.com/appleID",
      "updated_at": "2026-03-17 11:26:55"
    },
    {
      "id": "84032378eebb",
      "email": "saracortezuqwwr@icloud.com",
      "password": "1XeaKgYV21",
      "status": "正常",
      "country": "越南",
      "checked_at": "2026-03-17 11:29:38",
      "source": "ccbaohe.com/appleID",
      "updated_at": "2026-03-17 11:26:55"
    },
    {
      "id": "590b2ca7f0a8",
      "email": "victoriamahoneyazzbk@icloud.com",
      "password": "vP7R32CC9F",
      "status": "正常",
      "country": "印尼",
      "checked_at": "2026-03-17 11:29:38",
      "source": "ccbaohe.com/appleID",
      "updated_at": "2026-03-17 11:26:55"
    },
    {
      "id": "af1b3eee6778",
      "email": "robertmitchellkncfj@icloud.com",
      "password": "U5W1hyY6As",
      "status": "正常",
      "country": "美国",
      "checked_at": "2026-03-17 11:29:38",
      "source": "ccbaohe.com/appleID",
      "updated_at": "2026-03-17 11:26:55"
    },
    {
      "id": "3b801d4d90c7",
      "email": "michaellewisfdxzl@icloud.com",
      "password": "zP7X7yE5Sf",
      "status": "正常",
      "country": "越南",
      "checked_at": "2026-03-17 11:29:38",
      "source": "ccbaohe.com/appleID",
      "updated_at": "2026-03-17 11:26:55"
    },
    {
      "id": "e72e42788687",
      "email": "carlymorrisolcdv@icloud.com",
      "password": "2kUe89FWBs",
      "status": "正常",
      "country": "美国",
      "checked_at": "2026-03-17 11:29:38",
      "source": "ccbaohe.com/appleID",
      "updated_at": "2026-03-17 11:26:55"
    },
    {
      "id": "b0bb37862563",
      "email": "allisonharrisonzrhvh@icloud.com",
      "password": "MdWm73yjsK",
      "status": "正常",
      "country": "美国",
      "checked_at": "2026-03-17 11:29:38",
      "source": "ccbaohe.com/appleID",
      "updated_at": "2026-03-17 11:26:55"
    },
    {
      "id": "615875c5b35a",
      "email": "grantzamoragbejw@icloud.com",
      "password": "P3EYKCjEqn",
      "status": "正常",
      "country": "美国",
      "checked_at": "2026-03-17 11:29:38",
      "source": "ccbaohe.com/appleID",
      "updated_at": "2026-03-17 11:26:55"
    },
    {
      "id": "dbcb15675b78",
      "email": "orvexilad5pto@icloud.com",
      "password": "qJ2cZ2YPr7",
      "status": "正常",
      "country": "美国",
      "checked_at": "2026-03-17 11:29:38",
      "source": "ccbaohe.com/appleID",
      "updated_at": "2026-03-17 11:26:55"
    },
    {
      "id": "fc2161311961",
      "email": "raxodivle4kpa@icloud.com",
      "password": "H41uR1qVjd",
      "status": "正常",
      "country": "美国",
      "checked_at": "2026-03-17 11:29:38",
      "source": "ccbaohe.com/appleID",
      "updated_at": "2026-03-17 11:26:55"
    },
    {
      "id": "b9a66df243f4",
      "email": "quvexiral7mto@icloud.com",
      "password": "WV9FYdzdAJ",
      "status": "正常",
      "country": "美国",
      "checked_at": "2026-03-17 11:29:38",
      "source": "ccbaohe.com/appleID",
      "updated_at": "2026-03-17 11:26:55"
    },
    {
      "id": "1a2b6432f2d2",
      "email": "nbrvc11222@hotmail.com",
      "password": "RVdE5JjDWs",
      "status": "正常",
      "country": "美国",
      "checked_at": "2026-03-17 11:29:38",
      "source": "ccbaohe.com/appleID",
      "updated_at": "2026-03-17 11:26:55"
    },
    {
      "id": "e80bdeca0b8e",
      "email": "dpkjknd45561@hotmail.com",
      "password": "UnM6JFrANs",
      "status": "正常",
      "country": "美国",
      "checked_at": "2026-03-17 11:29:38",
      "source": "ccbaohe.com/appleID",
      "updated_at": "2026-03-17 11:26:55"
    },
    {
      "id": "fea2211629c7",
      "email": "rebeccageowalsh1c9@icloud.com",
      "password": "nX124ZWDSy",
      "status": "正常",
      "country": "美国",
      "checked_at": "2026-03-17 11:29:38",
      "source": "ccbaohe.com/appleID",
      "updated_at": "2026-03-17 11:26:55"
    },
    {
      "id": "43eadbfaec44",
      "email": "anthonpeterson5u9@icloud.com",
      "password": "KfK3pDS5fy",
      "status": "正常",
      "country": "美国",
      "checked_at": "2026-03-17 11:29:38",
      "source": "ccbaohe.com/appleID",
      "updated_at": "2026-03-17 11:26:55"
    },
    {
      "id": "c55c8f44e481",
      "email": "rebeccawhhall6j4@icloud.com",
      "password": "rbSrNc8nPA",
      "status": "正常",
      "country": "越南",
      "checked_at": "2026-03-17 11:29:38",
      "source": "ccbaohe.com/appleID",
      "updated_at": "2026-03-17 11:26:55"
    },
    {
      "id": "b4477fec192b",
      "email": "harrisjawiggins2e2@icloud.com",
      "password": "KNFhtmkK3a",
      "status": "正常",
      "country": "美国",
      "checked_at": "2026-03-17 11:29:38",
      "source": "ccbaohe.com/appleID",
      "updated_at": "2026-03-17 11:26:55"
    },
    {
      "id": "4ed227505325",
      "email": "julianmauhudson@outlook.com",
      "password": "TDNu8jGdpu9s",
      "status": "正常",
      "country": "越南",
      "checked_at": "2026-03-17 11:29:38",
      "source": "ccbaohe.com/appleID",
      "updated_at": "2026-03-17 11:26:55"
    },
    {
      "id": "6be16ca5c0e6",
      "email": "ojeovowc7810@hotmail.com",
      "password": "TDSY3djJN23Z",
      "status": "正常",
      "country": "美国",
      "checked_at": "2026-03-17 11:29:38",
      "source": "ccbaohe.com/appleID",
      "updated_at": "2026-03-17 11:26:55"
    },
    {
      "id": "65a137123a1b",
      "email": "eliasu2riley@outlook.com",
      "password": "TDaw1Hj4t8y2",
      "status": "正常",
      "country": "美国",
      "checked_at": "2026-03-17 11:29:38",
      "source": "ccbaohe.com/appleID",
      "updated_at": "2026-03-17 11:26:55"
    },
    {
      "id": "49909f9b168c",
      "email": "cbarwallace3a8@icloud.com",
      "password": "t!39rS!I",
      "status": "正常",
      "country": "美国",
      "checked_at": "2026-03-17 11:29:38",
      "source": "ccbaohe.com/appleID",
      "updated_at": "2026-03-17 11:26:55"
    },
    {
      "id": "9c1f2acd758e",
      "email": "zvmksii070361@icloud.com",
      "password": "Q12dU31j6Y",
      "status": "正常",
      "country": "美国",
      "checked_at": "2026-03-17 11:29:38",
      "source": "ccbaohe.com/appleID",
      "updated_at": "2026-03-17 11:26:55"
    },
    {
      "id": "b559fe152d71",
      "email": "kdzibli335026@icloud.com",
      "password": "zq1xaY7nt2",
      "status": "正常",
      "country": "香港",
      "checked_at": "2026-03-17 11:29:38",
      "source": "ccbaohe.com/appleID",
      "updated_at": "2026-03-17 11:26:55"
    },
    {
      "id": "3b80e49d57fd",
      "email": "wu985826536225@icloud.com",
      "password": "hC2utWEQUF",
      "status": "正常",
      "country": "澳大利亚",
      "checked_at": "2026-03-17 11:29:38",
      "source": "ccbaohe.com/appleID",
      "updated_at": "2026-03-17 11:26:55"
    },
    {
      "id": "fac2f0e1d9c5",
      "email": "carmensur63212@icloud.com",
      "password": "qtW1BxQykd",
      "status": "正常",
      "country": "越南",
      "checked_at": "2026-03-17 11:29:38",
      "source": "ccbaohe.com/appleID",
      "updated_at": "2026-03-17 11:26:55"
    },
    {
      "id": "f3106e5c7594",
      "email": "huai284600975@icloud.com",
      "password": "w4rsYnjQxh",
      "status": "正常",
      "country": "台湾",
      "checked_at": "2026-03-17 11:29:38",
      "source": "ccbaohe.com/appleID",
      "updated_at": "2026-03-17 11:26:55"
    },
    {
      "id": "6a596b376ac3",
      "email": "nwqmlkm724113@icloud.com",
      "password": "AKfVJymd5J",
      "status": "正常",
      "country": "香港",
      "checked_at": "2026-03-17 11:29:38",
      "source": "ccbaohe.com/appleID",
      "updated_at": "2026-03-17 11:26:55"
    },
    {
      "id": "b0129705843e",
      "email": "othvtoh347353@icloud.com",
      "password": "qE52k37m7k",
      "status": "正常",
      "country": "越南",
      "checked_at": "2026-03-17 11:29:38",
      "source": "ccbaohe.com/appleID",
      "updated_at": "2026-03-17 11:26:55"
    },
    {
      "id": "6709d8dbb792",
      "email": "mepjkjy374417@icloud.com",
      "password": "qer44uFECN",
      "status": "正常",
      "country": "美国",
      "checked_at": "2026-03-17 11:29:38",
      "source": "ccbaohe.com/appleID",
      "updated_at": "2026-03-17 11:26:55"
    },
    {
      "id": "68a216cd2c86",
      "email": "alswlln389627@icloud.com",
      "password": "mWJVmCKE7d",
      "status": "正常",
      "country": "马来西亚",
      "checked_at": "2026-03-17 11:29:38",
      "source": "ccbaohe.com/appleID",
      "updated_at": "2026-03-17 11:26:55"
    },
    {
      "id": "5ee2e5f6a45b",
      "email": "ousdxpf261614@icloud.com",
      "password": "pT3X2wCQ1j",
      "status": "正常",
      "country": "越南",
      "checked_at": "2026-03-17 11:29:38",
      "source": "ccbaohe.com/appleID",
      "updated_at": "2026-03-17 11:26:55"
    },
    {
      "id": "c54d3e107458",
      "email": "rwvidmf934559@icloud.com",
      "password": "eJECbEtKZ6",
      "status": "正常",
      "country": "越南",
      "checked_at": "2026-03-17 11:29:38",
      "source": "ccbaohe.com/appleID",
      "updated_at": "2026-03-17 11:26:55"
    },
    {
      "id": "9f4ada99f5e2",
      "email": "fugtdrn021306@icloud.com",
      "password": "mvDG6nZcVN",
      "status": "正常",
      "country": "土耳其",
      "checked_at": "2026-03-17 11:29:38",
      "source": "ccbaohe.com/appleID",
      "updated_at": "2026-03-17 11:26:55"
    },
    {
      "id": "b69adf058bcb",
      "email": "sjejxsq774991@icloud.com",
      "password": "TgzX7NZuCb",
      "status": "正常",
      "country": "越南",
      "checked_at": "2026-03-17 11:29:38",
      "source": "ccbaohe.com/appleID",
      "updated_at": "2026-03-17 11:26:55"
    },
    {
      "id": "d276c5760449",
      "email": "wvrflnw523@outlook.com",
      "password": "g6RT31jVFa",
      "status": "正常",
      "country": "美国",
      "checked_at": "2026-03-17 11:29:38",
      "source": "tkbaohe.com",
      "updated_at": "2026-03-17 11:27:37"
    },
    {
      "id": "bb3b1b94c69d",
      "email": "wkyqenytus@email.com",
      "password": "4gs4jPbtHw",
      "status": "正常",
      "country": "美国",
      "checked_at": "2026-03-17 11:29:38",
      "source": "tkbaohe.com",
      "updated_at": "2026-03-17 11:27:37"
    },
    {
      "id": "c43d89496c5f",
      "email": "miwyxuqijo06@email.com",
      "password": "yeRTK7mw49",
      "status": "正常",
      "country": "美国",
      "checked_at": "2026-03-17 11:29:38",
      "source": "tkbaohe.com",
      "updated_at": "2026-03-17 11:27:37"
    },
    {
      "id": "e3ed47e3c583",
      "email": "gtzqwxb291@hotmail.com",
      "password": "zBVavvmmW7",
      "status": "正常",
      "country": "美国",
      "checked_at": "2026-03-17 11:29:38",
      "source": "tkbaohe.com",
      "updated_at": "2026-03-17 11:27:37"
    },
    {
      "id": "8591ae0f862d",
      "email": "ehoviciwosibeb@email.com",
      "password": "QeSJfsJzB8",
      "status": "正常",
      "country": "美国",
      "checked_at": "2026-03-17 11:29:38",
      "source": "tkbaohe.com",
      "updated_at": "2026-03-17 11:27:37"
    },
    {
      "id": "1e3abf5c30d7",
      "email": "gjlaqdgdrz2484@outlook.com",
      "password": "4Swdth6Q7n",
      "status": "正常",
      "country": "美国",
      "checked_at": "2026-03-17 11:29:38",
      "source": "tkbaohe.com",
      "updated_at": "2026-03-17 11:27:37"
    },
    {
      "id": "783128eb7cd4",
      "email": "rowgxbyzpd556@outlook.com",
      "password": "dcfADdrM8q",
      "status": "正常",
      "country": "越南",
      "checked_at": "2026-03-17 11:29:38",
      "source": "tkbaohe.com",
      "updated_at": "2026-03-17 11:27:37"
    },
    {
      "id": "a7fe1171f30e",
      "email": "gbmzntmcm484@hotmail.com",
      "password": "r94brCkGmC",
      "status": "正常",
      "country": "越南",
      "checked_at": "2026-03-17 11:29:38",
      "source": "tkbaohe.com",
      "updated_at": "2026-03-17 11:27:37"
    },
    {
      "id": "6f2355d13ebc",
      "email": "o6gh6oby0f@icloud.com",
      "password": "Gzy7F46YNf",
      "status": "正常",
      "country": "香港",
      "checked_at": "2026-03-17 11:29:38",
      "source": "tkbaohe.com",
      "updated_at": "2026-03-17 11:27:37"
    },
    {
      "id": "334934d87a7b",
      "email": "ctkashley18414@icloud.com",
      "password": "gDymQ1ztTM",
      "status": "正常",
      "country": "日本",
      "checked_at": "2026-03-17 11:29:38",
      "source": "tkbaohe.com",
      "updated_at": "2026-03-17 11:27:37"
    },
    {
      "id": "ee60fc0d0876",
      "email": "meganreynobrooks9w4@icloud.com",
      "password": "ejeC8778bC",
      "status": "正常",
      "country": "香港",
      "checked_at": "2026-03-17 11:29:38",
      "source": "tkbaohe.com",
      "updated_at": "2026-03-17 11:27:37"
    },
    {
      "id": "6d65f57043eb",
      "email": "jamiebullsanchez8s6@icloud.com",
      "password": "6HhFaytH6S",
      "status": "正常",
      "country": "菲律宾",
      "checked_at": "2026-03-17 11:29:38",
      "source": "tkbaohe.com",
      "updated_at": "2026-03-17 11:27:37"
    },
    {
      "id": "7ecd161e9a15",
      "email": "williamolbest9v1@icloud.com",
      "password": "d5VYufvRhb",
      "status": "正常",
      "country": "美国",
      "checked_at": "2026-03-17 11:29:38",
      "source": "tkbaohe.com",
      "updated_at": "2026-03-17 11:27:37"
    },
    {
      "id": "2d7c99052f26",
      "email": "perezmichematthew8o7@icloud.com",
      "password": "ss5Dz9MzvC",
      "status": "正常",
      "country": "美国",
      "checked_at": "2026-03-17 11:29:38",
      "source": "tkbaohe.com",
      "updated_at": "2026-03-17 11:27:37"
    },
    {
      "id": "5c38a89aabda",
      "email": "xyumaria92408@icloud.com",
      "password": "Fxt5hqudxY",
      "status": "正常",
      "country": "美国",
      "checked_at": "2026-03-17 11:29:38",
      "source": "tkbaohe.com",
      "updated_at": "2026-03-17 11:27:37"
    },
    {
      "id": "a828dc629e5d",
      "email": "xdolinda22019@icloud.com",
      "password": "kQp7thUwKd",
      "status": "正常",
      "country": "越南",
      "checked_at": "2026-03-17 11:29:38",
      "source": "tkbaohe.com",
      "updated_at": "2026-03-17 11:27:37"
    },
    {
      "id": "02169d5b97b6",
      "email": "ritmarisol60135@icloud.com",
      "password": "dxhA2NX2aa",
      "status": "正常",
      "country": "日本",
      "checked_at": "2026-03-17 11:29:38",
      "source": "tkbaohe.com",
      "updated_at": "2026-03-17 11:27:37"
    },
    {
      "id": "d48f5f0942bc",
      "email": "zacharysimonjxnwg@icloud.com",
      "password": "HFW2mmBjJM",
      "status": "正常",
      "country": "台湾",
      "checked_at": "2026-03-17 11:29:38",
      "source": "tkbaohe.com",
      "updated_at": "2026-03-17 11:27:37"
    },
    {
      "id": "fecd504be5c0",
      "email": "staceysmithhuaid@icloud.com",
      "password": "Zfe8sbS2zE",
      "status": "正常",
      "country": "越南",
      "checked_at": "2026-03-17 11:29:38",
      "source": "tkbaohe.com",
      "updated_at": "2026-03-17 11:27:37"
    },
    {
      "id": "b682c04a82f8",
      "email": "adamstarkiuifu@icloud.com",
      "password": "nCV5rWDXeV",
      "status": "正常",
      "country": "美国",
      "checked_at": "2026-03-17 11:29:38",
      "source": "tkbaohe.com",
      "updated_at": "2026-03-17 11:27:37"
    },
    {
      "id": "f7b5edfbad1a",
      "email": "shanewestytvfx@icloud.com",
      "password": "smK1Sx41SS",
      "status": "正常",
      "country": "越南",
      "checked_at": "2026-03-17 11:29:38",
      "source": "tkbaohe.com",
      "updated_at": "2026-03-17 11:27:37"
    },
    {
      "id": "2ab194b2bb15",
      "email": "gestascumbibendu6@icloud.com",
      "password": "gPQ8JgM7Mc",
      "status": "正常",
      "country": "美国",
      "checked_at": "2026-03-17 11:28:11",
      "source": "id.btvda.top",
      "updated_at": "2026-03-17 11:28:11"
    },
    {
      "id": "981070a08b40",
      "email": "mvzicmbu2757@outlook.com",
      "password": "PkSFXu7EAN",
      "status": "正常",
      "country": "美国",
      "checked_at": "2026-03-17 11:28:11",
      "source": "id.btvda.top",
      "updated_at": "2026-03-17 11:28:11"
    },
    {
      "id": "742202e4adee",
      "email": "tconv98411823@icloud.com",
      "password": "sTuyNd7r5M",
      "status": "正常",
      "country": "美国",
      "checked_at": "2026-03-17 11:28:11",
      "source": "id.btvda.top",
      "updated_at": "2026-03-17 11:28:11"
    },
    {
      "id": "12b128f1af70",
      "email": "tycushepavy@outlook.com",
      "password": "zjGA6nEjvR",
      "status": "正常",
      "country": "美国",
      "checked_at": "2026-03-17 11:28:11",
      "source": "id.btvda.top",
      "updated_at": "2026-03-17 11:28:11"
    },
    {
      "id": "bbb150cc7109",
      "email": "ai_tc50737659@icloud.com",
      "password": "TVb9RmX3Ua",
      "status": "正常",
      "country": "美国",
      "checked_at": "2026-03-17 11:28:11",
      "source": "id.btvda.top",
      "updated_at": "2026-03-17 11:28:11"
    },
    {
      "id": "82d40933cb69",
      "email": "tesqueiac.ulis.918@icloud.com",
      "password": "8yAkzn3bAF",
      "status": "正常",
      "country": "美国",
      "checked_at": "2026-03-17 11:28:11",
      "source": "id.btvda.top",
      "updated_at": "2026-03-17 11:28:11"
    },
    {
      "id": "c2027aee7898",
      "email": "rv77948142chaola@163.com",
      "password": "G8YcfFSKr2",
      "status": "正常",
      "country": "越南",
      "checked_at": "2026-03-17 11:28:11",
      "source": "id.btvda.top",
      "updated_at": "2026-03-17 11:28:11"
    },
    {
      "id": "371387a82763",
      "email": "jrice3tn@hotmail.com",
      "password": "B6F6Z21DRa",
      "status": "正常",
      "country": "英国",
      "checked_at": "2026-03-17 11:28:11",
      "source": "id.btvda.top",
      "updated_at": "2026-03-17 11:28:11"
    },
    {
      "id": "1797eb17bb4b",
      "email": "helennrr74483@icloud.com",
      "password": "HJCKXP2Wn2",
      "status": "正常",
      "country": "美国",
      "checked_at": "2026-03-17 11:28:11",
      "source": "id.btvda.top",
      "updated_at": "2026-03-17 11:28:11"
    },
    {
      "id": "0e894ea0dc03",
      "email": "jaydenbwolson@hotmail.com",
      "password": "SDg17n22",
      "status": "正常",
      "country": "美国",
      "checked_at": "2026-03-17 11:28:11",
      "source": "id.btvda.top",
      "updated_at": "2026-03-17 11:28:11"
    },
    {
      "id": "7c8a856318b8",
      "email": "ma6rc6o4po9r@icloud.com",
      "password": "3kSQ9KTNgV",
      "status": "正常",
      "country": "美国",
      "checked_at": "2026-03-17 11:29:38",
      "source": "id.btvda.top",
      "updated_at": "2026-03-17 11:28:11"
    },
    {
      "id": "12fbfb5c032e",
      "email": "crystaljamespwuhj@icloud.com",
      "password": "DdA8dEnt7q",
      "status": "正常",
      "country": "美国",
      "checked_at": "2026-03-17 11:29:38",
      "source": "id.bocchi2b.top",
      "updated_at": "2026-03-17 11:29:38"
    },
    {
      "id": "0f60a3be6f26",
      "email": "ryanmoodybhfpi@icloud.com",
      "password": "sPpxpaRuh7",
      "status": "正常",
      "country": "美国",
      "checked_at": "2026-03-17 11:29:38",
      "source": "id.bocchi2b.top",
      "updated_at": "2026-03-17 11:29:38"
    },
    {
      "id": "c3210bf290b4",
      "email": "catherinejohnsoylsw@icloud.com",
      "password": "Z5HkesP7qg",
      "status": "正常",
      "country": "越南",
      "checked_at": "2026-03-17 11:29:38",
      "source": "id.bocchi2b.top",
      "updated_at": "2026-03-17 11:29:38"
    },
    {
      "id": "533e37a7e10d",
      "email": "lisawhitebnzxz@icloud.com",
      "password": "gWBMwsDHp8",
      "status": "正常",
      "country": "马来西亚",
      "checked_at": "2026-03-17 11:29:38",
      "source": "id.bocchi2b.top",
      "updated_at": "2026-03-17 11:29:38"
    },
    {
      "id": "f2d627d57e9a",
      "email": "whitneypowellusuuk@icloud.com",
      "password": "eSFF19jRPm",
      "status": "正常",
      "country": "美国",
      "checked_at": "2026-03-17 11:29:38",
      "source": "id.bocchi2b.top",
      "updated_at": "2026-03-17 11:29:38"
    },
    {
      "id": "767dfd7037bc",
      "email": "richardhayestrwmx@icloud.com",
      "password": "te8zAK5Qmr",
      "status": "正常",
      "country": "美国",
      "checked_at": "2026-03-17 11:29:38",
      "source": "id.bocchi2b.top",
      "updated_at": "2026-03-17 11:29:38"
    },
    {
      "id": "e32e583a44fc",
      "email": "jilliancookwtwrf@icloud.com",
      "password": "N1QnZNzsts",
      "status": "正常",
      "country": "印尼",
      "checked_at": "2026-03-17 11:29:38",
      "source": "id.bocchi2b.top",
      "updated_at": "2026-03-17 11:29:38"
    },
    {
      "id": "115720b9e44d",
      "email": "mznra316@hotmail.com",
      "password": "6VRQXu5pgf",
      "status": "正常",
      "country": "美国",
      "checked_at": "2026-03-17 11:29:38",
      "source": "id.bocchi2b.top",
      "updated_at": "2026-03-17 11:29:38"
    },
    {
      "id": "9ff422f2141c",
      "email": "etlbarbara90242@icloud.com",
      "password": "cvTsvk66ya",
      "status": "正常",
      "country": "越南",
      "checked_at": "2026-03-17 11:29:38",
      "source": "id.bocchi2b.top",
      "updated_at": "2026-03-17 11:29:38"
    }
  ]
}